homevisit/__init__.py
homevisit/admin.py
homevisit/apps.py
homevisit/forms.py
homevisit/models.py
homevisit/test_forms.py
homevisit/test_models.py
homevisit/test_views.py
homevisit/urls.py
homevisit/views.py
homevisit/migrations/0001_initial.py
homevisit/migrations/0002_feedback.py
homevisit/migrations/0003_faq.py
homevisit/migrations/__init__.py
homevisit_project/__init__.py
homevisit_project/settings.py
homevisit_project/urls.py
homevisit_project/wsgi.py
homevisit-0.0.1.dist-info/LICENSE
homevisit-0.0.1.dist-info/METADATA
homevisit-0.0.1.dist-info/WHEEL
homevisit-0.0.1.dist-info/top_level.txt
homevisit-0.0.1.dist-info/RECORD
