Metadata-Version: 2.1
Name: homevisit
Version: 0.0.1
Summary: Helps organize and plan pastor home visits
Home-page: https://github.com/curtis628/homevisit
Author: Tyler Curtis
Author-email: tjcurt@gmail.com
License: UNKNOWN
Platform: UNKNOWN
Classifier: Programming Language :: Python :: 3
Classifier: License :: OSI Approved :: Apache Software License
Classifier: Operating System :: OS Independent
Requires-Dist: django
Requires-Dist: django-phonenumber-field
Requires-Dist: phonenumbers
Requires-Dist: django-crispy-forms
